zazzle/__init__.py
zazzle/zz_logging.py
Zazzle-0.1.6.dist-info/LICENSE
Zazzle-0.1.6.dist-info/METADATA
Zazzle-0.1.6.dist-info/WHEEL
Zazzle-0.1.6.dist-info/top_level.txt
Zazzle-0.1.6.dist-info/zip-safe
Zazzle-0.1.6.dist-info/RECORD
